odoo/addons/sale_order_line_not_billable/README.rst
odoo/addons/sale_order_line_not_billable/__init__.py
odoo/addons/sale_order_line_not_billable/__manifest__.py
odoo/addons/sale_order_line_not_billable/i18n/de.po
odoo/addons/sale_order_line_not_billable/i18n/sale_order_line_not_billable.pot
odoo/addons/sale_order_line_not_billable/models/__init__.py
odoo/addons/sale_order_line_not_billable/models/product_template.py
odoo/addons/sale_order_line_not_billable/models/sale_order.py
odoo/addons/sale_order_line_not_billable/models/sale_order_line.py
odoo/addons/sale_order_line_not_billable/readme/CONTRIBUTORS.rst
odoo/addons/sale_order_line_not_billable/readme/CREDITS.rst
odoo/addons/sale_order_line_not_billable/readme/DESCRIPTION.rst
odoo/addons/sale_order_line_not_billable/readme/USAGE.rst
odoo/addons/sale_order_line_not_billable/static/description/icon.png
odoo/addons/sale_order_line_not_billable/static/description/index.html
odoo/addons/sale_order_line_not_billable/views/product_template.xml
odoo_addon_sale_order_line_not_billable-15.0.1.0.0.2.dist-info/METADATA
odoo_addon_sale_order_line_not_billable-15.0.1.0.0.2.dist-info/WHEEL
odoo_addon_sale_order_line_not_billable-15.0.1.0.0.2.dist-info/top_level.txt
odoo_addon_sale_order_line_not_billable-15.0.1.0.0.2.dist-info/RECORD
